flash_accounts/__init__.py
flash_accounts/admin.py
flash_accounts/apps.py
flash_accounts/models.py
flash_accounts/serializers.py
flash_accounts/services.py
flash_accounts/settings.py
flash_accounts/tests.py
flash_accounts/urls.py
flash_accounts/views.py
flash_accounts/migrations/0001_initial.py
flash_accounts/migrations/__init__.py
flash_accounts/templates/flash_accounts/activate.html
flash_accounts/templates/flash_accounts/activate.txt
flash_accounts/templates/flash_accounts/password_reset.html
flash_accounts/templates/flash_accounts/password_reset.txt
flash_accounts-1.0.1.dist-info/LICENSE
flash_accounts-1.0.1.dist-info/METADATA
flash_accounts-1.0.1.dist-info/WHEEL
flash_accounts-1.0.1.dist-info/top_level.txt
flash_accounts-1.0.1.dist-info/RECORD
