Metadata-Version: 2.1
Name: flash-accounts
Version: 1.0.1
Summary: DRF lightweight reusable app for account management
Author: Mateusz Meksuła
License: MIT
Project-URL: Homepage, https://github.com/MeksulaM/flash-accounts
Keywords: django,restframework,djangorestframework,authentication
Classifier: Development Status :: 5 - Production/Stable
Classifier: Environment :: Web Environment
Classifier: Intended Audience :: Developers
Classifier: Operating System :: OS Independent
Classifier: License :: OSI Approved :: MIT License
Classifier: Programming Language :: Python :: 3
Classifier: Framework :: Django
Requires-Python: >=3.7
License-File: LICENSE
Requires-Dist: django (>=3.0)
Requires-Dist: djangorestframework (>=3.11.0)
